CTK_Desert/AddPage.py
CTK_Desert/Core.py
CTK_Desert/Page_EX_Code.py
CTK_Desert/Page_base_model.py
CTK_Desert/Settings.py
CTK_Desert/Tab_Page_Frame.py
CTK_Desert/Theme.py
CTK_Desert/Top_level_dialog.py
CTK_Desert/Widgits.py
CTK_Desert/Workspace.py
CTK_Desert/__init__.py
CTK_Desert/preferences.json
CTK_Desert/utils.py
CTK_Desert/images/empty.ico
CTK_Desert/images/preview_window.png
CTK_Desert/images/Icons/icons8-delete-64.png
CTK_Desert/images/Icons/icons8-edit-64.png
CTK_Desert/images/Icons/icons8-right-arrow-64.png
CTK_Desert/images/Icons/settings_d.png
CTK_Desert/images/Icons/settings_d_s.png
CTK_Desert/images/Icons/settings_l.png
CTK_Desert/images/Icons/settings_l_s.png
CTK_Desert/images/Icons/workspace_d.png
CTK_Desert/images/Icons/workspace_d_s.png
CTK_Desert/images/Icons/workspace_l.png
CTK_Desert/images/Icons/workspace_l_s.png
CTK_Desert-0.0.67.dist-info/LICENSE
CTK_Desert-0.0.67.dist-info/METADATA
CTK_Desert-0.0.67.dist-info/WHEEL
CTK_Desert-0.0.67.dist-info/top_level.txt
CTK_Desert-0.0.67.dist-info/RECORD
