Metadata-Version: 2.1
Name: CTK_Desert
Version: 0.0.67
Summary: A GUI that uses the customtkinter library to create GUIs based on your need, so that you focus on the functionality of your application and not the design.
Author-email: Morad Sayed <Morad.S.Singer@gmail.com>
License: Attribution-NonCommercial 4.0 International
Keywords: CTK_Desert,tkinter,Customtkinter,GUI,APP,beautiful,design,easy,simple,fast,CTK
Classifier: Development Status :: 3 - Alpha
Classifier: Intended Audience :: Developers
Classifier: Programming Language :: Python :: 3 :: Only
Classifier: License :: Other/Proprietary License
Classifier: Operating System :: Microsoft :: Windows
Requires-Python: <4.0,>=3.8
License-File: LICENSE
Requires-Dist: customtkinter <6.0.0,>=5.2.0
Requires-Dist: Pillow <11.0.0,>=9.4.0
Requires-Dist: numpy <2.0.0,>=1.23.5
Requires-Dist: pywin32 <310,>=305
